odoo8_addon_web_widget_digitized_signature_user-8.0.1.0.0.99.dev12-py2.7-nspkg.pth
odoo8_addon_web_widget_digitized_signature_user-8.0.1.0.0.99.dev12.dist-info/DESCRIPTION.rst
odoo8_addon_web_widget_digitized_signature_user-8.0.1.0.0.99.dev12.dist-info/METADATA
odoo8_addon_web_widget_digitized_signature_user-8.0.1.0.0.99.dev12.dist-info/RECORD
odoo8_addon_web_widget_digitized_signature_user-8.0.1.0.0.99.dev12.dist-info/WHEEL
odoo8_addon_web_widget_digitized_signature_user-8.0.1.0.0.99.dev12.dist-info/metadata.json
odoo8_addon_web_widget_digitized_signature_user-8.0.1.0.0.99.dev12.dist-info/namespace_packages.txt
odoo8_addon_web_widget_digitized_signature_user-8.0.1.0.0.99.dev12.dist-info/top_level.txt
odoo_addons/web_widget_digitized_signature_user/README.rst
odoo_addons/web_widget_digitized_signature_user/__init__.py
odoo_addons/web_widget_digitized_signature_user/__openerp__.py
odoo_addons/web_widget_digitized_signature_user/i18n/ar.po
odoo_addons/web_widget_digitized_signature_user/i18n/ca.po
odoo_addons/web_widget_digitized_signature_user/i18n/de.po
odoo_addons/web_widget_digitized_signature_user/i18n/el_GR.po
odoo_addons/web_widget_digitized_signature_user/i18n/es.po
odoo_addons/web_widget_digitized_signature_user/i18n/es_ES.po
odoo_addons/web_widget_digitized_signature_user/i18n/eu.po
odoo_addons/web_widget_digitized_signature_user/i18n/fi.po
odoo_addons/web_widget_digitized_signature_user/i18n/fr.po
odoo_addons/web_widget_digitized_signature_user/i18n/fr_CH.po
odoo_addons/web_widget_digitized_signature_user/i18n/hr.po
odoo_addons/web_widget_digitized_signature_user/i18n/hr_HR.po
odoo_addons/web_widget_digitized_signature_user/i18n/it.po
odoo_addons/web_widget_digitized_signature_user/i18n/nl.po
odoo_addons/web_widget_digitized_signature_user/i18n/pt_BR.po
odoo_addons/web_widget_digitized_signature_user/i18n/sl.po
odoo_addons/web_widget_digitized_signature_user/i18n/tr.po
odoo_addons/web_widget_digitized_signature_user/i18n/tr_TR.po
odoo_addons/web_widget_digitized_signature_user/i18n/web_widget_digitized_signature_user.pot
odoo_addons/web_widget_digitized_signature_user/i18n/zh_CN.po
odoo_addons/web_widget_digitized_signature_user/models/__init__.py
odoo_addons/web_widget_digitized_signature_user/models/users.py
odoo_addons/web_widget_digitized_signature_user/static/description/icon.png
odoo_addons/web_widget_digitized_signature_user/views/users_view.xml
